<annotation>
	<folder>Mask</folder>
	<filename>processedMask.avi</filename>
	<path>C:\Users\55126524\Desktop\CIIT\Data\Mask\processedMask.avi</path>
	<source>
		<database>Unknown</database>
	</source>
	<size>
		<width>1920</width>
		<height>910</height>
		<depth>3</depth>
	</size>
	<segmented>0</segmented>
	<object>
		<name>NM</name>
		<id>23</id>
		<pose>Unspecified</pose>
		<truncated>0</truncated>
		<difficult>0</difficult>
		<bndbox>
			<xmin>476</xmin>
			<ymin>221</ymin>
			<xmax>638</xmax>
			<ymax>429</ymax>
		</bndbox>
	</object>
	<object>
		<name>MW</name>
		<id>3</id>
		<pose>Unspecified</pose>
		<truncated>0</truncated>
		<difficult>0</difficult>
		<bndbox>
			<xmin>870</xmin>
			<ymin>406</ymin>
			<xmax>1003</xmax>
			<ymax>805</ymax>
		</bndbox>
	</object>
	<object>
		<name>NM</name>
		<id>4</id>
		<pose>Unspecified</pose>
		<truncated>0</truncated>
		<difficult>0</difficult>
		<bndbox>
			<xmin>1275</xmin>
			<ymin>275</ymin>
			<xmax>1407</xmax>
			<ymax>606</ymax>
		</bndbox>
	</object>
	<object>
		<name>NM</name>
		<id>24</id>
		<pose>Unspecified</pose>
		<truncated>0</truncated>
		<difficult>0</difficult>
		<bndbox>
			<xmin>1111</xmin>
			<ymin>425</ymin>
			<xmax>1280</xmax>
			<ymax>868</ymax>
		</bndbox>
	</object>
</annotation>
