<annotation>
	<folder>Mask</folder>
	<filename>processedMask.avi</filename>
	<path>C:\Users\55126524\Desktop\CIIT\Data\Mask\processedMask.avi</path>
	<source>
		<database>Unknown</database>
	</source>
	<size>
		<width>1920</width>
		<height>910</height>
		<depth>3</depth>
	</size>
	<segmented>0</segmented>
	<object>
		<name>NM</name>
		<id>0</id>
		<pose>Unspecified</pose>
		<truncated>0</truncated>
		<difficult>0</difficult>
		<bndbox>
			<xmin>1197</xmin>
			<ymin>50</ymin>
			<xmax>1315</xmax>
			<ymax>264</ymax>
		</bndbox>
	</object>
	<object>
		<name>MW</name>
		<id>16</id>
		<pose>Unspecified</pose>
		<truncated>0</truncated>
		<difficult>0</difficult>
		<bndbox>
			<xmin>530</xmin>
			<ymin>338</ymin>
			<xmax>662</xmax>
			<ymax>641</ymax>
		</bndbox>
	</object>
	<object>
		<name>NM</name>
		<id>22</id>
		<pose>Unspecified</pose>
		<truncated>0</truncated>
		<difficult>0</difficult>
		<bndbox>
			<xmin>624</xmin>
			<ymin>24</ymin>
			<xmax>749</xmax>
			<ymax>284</ymax>
		</bndbox>
	</object>
	<object>
		<name>NM</name>
		<id>1</id>
		<pose>Unspecified</pose>
		<truncated>0</truncated>
		<difficult>0</difficult>
		<bndbox>
			<xmin>1078</xmin>
			<ymin>140</ymin>
			<xmax>1188</xmax>
			<ymax>408</ymax>
		</bndbox>
	</object>
	<object>
		<name>NM</name>
		<id>5</id>
		<pose>Unspecified</pose>
		<truncated>0</truncated>
		<difficult>0</difficult>
		<bndbox>
			<xmin>827</xmin>
			<ymin>245</ymin>
			<xmax>975</xmax>
			<ymax>605</ymax>
		</bndbox>
	</object>
</annotation>
