<annotation>
	<folder>Mask</folder>
	<filename>processedMask.avi</filename>
	<path>C:\Users\55126524\Desktop\CIIT\Data\Mask\processedMask.avi</path>
	<source>
		<database>Unknown</database>
	</source>
	<size>
		<width>1920</width>
		<height>910</height>
		<depth>3</depth>
	</size>
	<segmented>0</segmented>
	<object>
		<name>NM</name>
		<id>19</id>
		<pose>Unspecified</pose>
		<truncated>0</truncated>
		<difficult>0</difficult>
		<bndbox>
			<xmin>480</xmin>
			<ymin>214</ymin>
			<xmax>590</xmax>
			<ymax>568</ymax>
		</bndbox>
	</object>
	<object>
		<name>NM</name>
		<id>20</id>
		<pose>Unspecified</pose>
		<truncated>0</truncated>
		<difficult>0</difficult>
		<bndbox>
			<xmin>574</xmin>
			<ymin>192</ymin>
			<xmax>697</xmax>
			<ymax>573</ymax>
		</bndbox>
	</object>
	<object>
		<name>NM</name>
		<id>18</id>
		<pose>Unspecified</pose>
		<truncated>0</truncated>
		<difficult>0</difficult>
		<bndbox>
			<xmin>698</xmin>
			<ymin>208</ymin>
			<xmax>827</xmax>
			<ymax>538</ymax>
		</bndbox>
	</object>
	<object>
		<name>MW</name>
		<id>15</id>
		<pose>Unspecified</pose>
		<truncated>0</truncated>
		<difficult>0</difficult>
		<bndbox>
			<xmin>1168</xmin>
			<ymin>361</ymin>
			<xmax>1318</xmax>
			<ymax>697</ymax>
		</bndbox>
	</object>
	<object>
		<name>MW</name>
		<id>17</id>
		<pose>Unspecified</pose>
		<truncated>0</truncated>
		<difficult>0</difficult>
		<bndbox>
			<xmin>1149</xmin>
			<ymin>249</ymin>
			<xmax>1277</xmax>
			<ymax>487</ymax>
		</bndbox>
	</object>
	<object>
		<name>NM</name>
		<id>21</id>
		<pose>Unspecified</pose>
		<truncated>0</truncated>
		<difficult>0</difficult>
		<bndbox>
			<xmin>953</xmin>
			<ymin>91</ymin>
			<xmax>1053</xmax>
			<ymax>390</ymax>
		</bndbox>
	</object>
	<object>
		<name>NM</name>
		<id>0</id>
		<pose>Unspecified</pose>
		<truncated>0</truncated>
		<difficult>0</difficult>
		<bndbox>
			<xmin>1570</xmin>
			<ymin>586</ymin>
			<xmax>1766</xmax>
			<ymax>883</ymax>
		</bndbox>
	</object>
</annotation>
