<annotation>
	<folder>Mask</folder>
	<filename>processedMask.avi</filename>
	<path>C:\Users\55126524\Desktop\CIIT\Data\Mask\processedMask.avi</path>
	<source>
		<database>Unknown</database>
	</source>
	<size>
		<width>1920</width>
		<height>910</height>
		<depth>3</depth>
	</size>
	<segmented>0</segmented>
	<object>
		<name>NM</name>
		<id>16</id>
		<pose>Unspecified</pose>
		<truncated>0</truncated>
		<difficult>0</difficult>
		<bndbox>
			<xmin>925</xmin>
			<ymin>287</ymin>
			<xmax>1034</xmax>
			<ymax>563</ymax>
		</bndbox>
	</object>
	<object>
		<name>NM</name>
		<id>24</id>
		<pose>Unspecified</pose>
		<truncated>0</truncated>
		<difficult>0</difficult>
		<bndbox>
			<xmin>698</xmin>
			<ymin>320</ymin>
			<xmax>822</xmax>
			<ymax>687</ymax>
		</bndbox>
	</object>
	<object>
		<name>NM</name>
		<id>26</id>
		<pose>Unspecified</pose>
		<truncated>0</truncated>
		<difficult>0</difficult>
		<bndbox>
			<xmin>917</xmin>
			<ymin>85</ymin>
			<xmax>1025</xmax>
			<ymax>365</ymax>
		</bndbox>
	</object>
	<object>
		<name>NM</name>
		<id>1</id>
		<pose>Unspecified</pose>
		<truncated>0</truncated>
		<difficult>0</difficult>
		<bndbox>
			<xmin>1414</xmin>
			<ymin>460</ymin>
			<xmax>1586</xmax>
			<ymax>881</ymax>
		</bndbox>
	</object>
</annotation>
