<annotation>
	<folder>Mask</folder>
	<filename>processedMask.avi</filename>
	<path>C:\Users\55126524\Desktop\CIIT\Data\Mask\processedMask.avi</path>
	<source>
		<database>Unknown</database>
	</source>
	<size>
		<width>1920</width>
		<height>910</height>
		<depth>3</depth>
	</size>
	<segmented>0</segmented>
	<object>
		<name>MW</name>
		<id>0</id>
		<pose>Unspecified</pose>
		<truncated>0</truncated>
		<difficult>0</difficult>
		<bndbox>
			<xmin>901</xmin>
			<ymin>394</ymin>
			<xmax>1045</xmax>
			<ymax>728</ymax>
		</bndbox>
	</object>
	<object>
		<name>NM</name>
		<id>3</id>
		<pose>Unspecified</pose>
		<truncated>0</truncated>
		<difficult>0</difficult>
		<bndbox>
			<xmin>931</xmin>
			<ymin>53</ymin>
			<xmax>1009</xmax>
			<ymax>257</ymax>
		</bndbox>
	</object>
	<object>
		<name>NM</name>
		<id>4</id>
		<pose>Unspecified</pose>
		<truncated>0</truncated>
		<difficult>0</difficult>
		<bndbox>
			<xmin>1073</xmin>
			<ymin>118</ymin>
			<xmax>1215</xmax>
			<ymax>409</ymax>
		</bndbox>
	</object>
	<object>
		<name>MW</name>
		<id>1</id>
		<pose>Unspecified</pose>
		<truncated>0</truncated>
		<difficult>0</difficult>
		<bndbox>
			<xmin>668</xmin>
			<ymin>4</ymin>
			<xmax>778</xmax>
			<ymax>273</ymax>
		</bndbox>
	</object>
</annotation>
