<annotation>
	<folder>Mask</folder>
	<filename>processedMask.avi</filename>
	<path>C:\Users\55126524\Desktop\CIIT\Data\Mask\processedMask.avi</path>
	<source>
		<database>Unknown</database>
	</source>
	<size>
		<width>1920</width>
		<height>910</height>
		<depth>3</depth>
	</size>
	<segmented>0</segmented>
	<object>
		<name>NM</name>
		<id>16</id>
		<pose>Unspecified</pose>
		<truncated>0</truncated>
		<difficult>0</difficult>
		<bndbox>
			<xmin>445</xmin>
			<ymin>598</ymin>
			<xmax>601</xmax>
			<ymax>935</ymax>
		</bndbox>
	</object>
	<object>
		<name>NM</name>
		<id>26</id>
		<pose>Unspecified</pose>
		<truncated>0</truncated>
		<difficult>0</difficult>
		<bndbox>
			<xmin>964</xmin>
			<ymin>399</ymin>
			<xmax>1072</xmax>
			<ymax>684</ymax>
		</bndbox>
	</object>
	<object>
		<name>NM</name>
		<id>1</id>
		<pose>Unspecified</pose>
		<truncated>0</truncated>
		<difficult>0</difficult>
		<bndbox>
			<xmin>1108</xmin>
			<ymin>228</ymin>
			<xmax>1224</xmax>
			<ymax>578</ymax>
		</bndbox>
	</object>
	<object>
		<name>MW</name>
		<id>22</id>
		<pose>Unspecified</pose>
		<truncated>0</truncated>
		<difficult>0</difficult>
		<bndbox>
			<xmin>588</xmin>
			<ymin>101</ymin>
			<xmax>698</xmax>
			<ymax>317</ymax>
		</bndbox>
	</object>
	<object>
		<name>NM</name>
		<id>25</id>
		<pose>Unspecified</pose>
		<truncated>0</truncated>
		<difficult>0</difficult>
		<bndbox>
			<xmin>1210</xmin>
			<ymin>14</ymin>
			<xmax>1302</xmax>
			<ymax>240</ymax>
		</bndbox>
	</object>
	<object>
		<name>MW</name>
		<id>5</id>
		<pose>Unspecified</pose>
		<truncated>0</truncated>
		<difficult>0</difficult>
		<bndbox>
			<xmin>1045</xmin>
			<ymin>13</ymin>
			<xmax>1137</xmax>
			<ymax>258</ymax>
		</bndbox>
	</object>
</annotation>
