<annotation>
	<folder>Mask</folder>
	<filename>processedMask.avi</filename>
	<path>C:\Users\55126524\Desktop\CIIT\Data\Mask\processedMask.avi</path>
	<source>
		<database>Unknown</database>
	</source>
	<size>
		<width>1920</width>
		<height>910</height>
		<depth>3</depth>
	</size>
	<segmented>0</segmented>
	<object>
		<name>NM</name>
		<id>0</id>
		<pose>Unspecified</pose>
		<truncated>0</truncated>
		<difficult>0</difficult>
		<bndbox>
			<xmin>1325</xmin>
			<ymin>166</ymin>
			<xmax>1448</xmax>
			<ymax>443</ymax>
		</bndbox>
	</object>
	<object>
		<name>NM</name>
		<id>25</id>
		<pose>Unspecified</pose>
		<truncated>0</truncated>
		<difficult>0</difficult>
		<bndbox>
			<xmin>1468</xmin>
			<ymin>473</ymin>
			<xmax>1634</xmax>
			<ymax>856</ymax>
		</bndbox>
	</object>
	<object>
		<name>NM</name>
		<id>16</id>
		<pose>Unspecified</pose>
		<truncated>0</truncated>
		<difficult>0</difficult>
		<bndbox>
			<xmin>1169</xmin>
			<ymin>-34</ymin>
			<xmax>1255</xmax>
			<ymax>186</ymax>
		</bndbox>
	</object>
	<object>
		<name>NM</name>
		<id>22</id>
		<pose>Unspecified</pose>
		<truncated>0</truncated>
		<difficult>0</difficult>
		<bndbox>
			<xmin>444</xmin>
			<ymin>380</ymin>
			<xmax>569</xmax>
			<ymax>730</ymax>
		</bndbox>
	</object>
	<object>
		<name>MW</name>
		<id>1</id>
		<pose>Unspecified</pose>
		<truncated>0</truncated>
		<difficult>0</difficult>
		<bndbox>
			<xmin>850</xmin>
			<ymin>16</ymin>
			<xmax>946</xmax>
			<ymax>249</ymax>
		</bndbox>
	</object>
	<object>
		<name>MW</name>
		<id>3</id>
		<pose>Unspecified</pose>
		<truncated>0</truncated>
		<difficult>0</difficult>
		<bndbox>
			<xmin>904</xmin>
			<ymin>137</ymin>
			<xmax>1003</xmax>
			<ymax>356</ymax>
		</bndbox>
	</object>
	<object>
		<name>NM</name>
		<id>4</id>
		<pose>Unspecified</pose>
		<truncated>0</truncated>
		<difficult>0</difficult>
		<bndbox>
			<xmin>1055</xmin>
			<ymin>74</ymin>
			<xmax>1182</xmax>
			<ymax>356</ymax>
		</bndbox>
	</object>
</annotation>
